textual_file_viewer/FiraCode-Medium.ttf
textual_file_viewer/__init__.py
textual_file_viewer/dicom_tree.py
textual_file_viewer/dicom_viewer.py
textual_file_viewer/file_viewer.py
textual_file_viewer/file_viewer.tcss
textual_file_viewer/image_viewer.py
textual_file_viewer/mhd_nifti_viewer.py
textual_file_viewer-0.9.0.dist-info/METADATA
textual_file_viewer-0.9.0.dist-info/WHEEL
textual_file_viewer-0.9.0.dist-info/entry_points.txt
textual_file_viewer-0.9.0.dist-info/RECORD
